fernet_inspector
