Metadata-Version: 1.1
Name: fernet-inspector
Version: 0.1.3
Summary: inspect fernet tokens generated by keystone
Home-page: https://github.com/lbragstad/fernet-inspector
Author: Lance Bragstad
Author-email: lbragstad@gmail.com
License: Apache Software License
Platform: UNKNOWN
Classifier: Development Status :: 3 - Alpha
Classifier: Intended Audience :: Developers
Classifier: License :: OSI Approved :: Apache Software License
Classifier: Natural Language :: English
Classifier: Operating System :: OS Independent
Classifier: Programming Language :: Python
Classifier: Topic :: Software Development :: Testing
